mkdocs_ko_fi_button_plugin/__init__.py
mkdocs_ko_fi_button_plugin/mkdocs_ko_fi_button_plugin.py
mkdocs_ko_fi_button_plugin-0.0.3.dist-info/LICENSE
mkdocs_ko_fi_button_plugin-0.0.3.dist-info/METADATA
mkdocs_ko_fi_button_plugin-0.0.3.dist-info/WHEEL
mkdocs_ko_fi_button_plugin-0.0.3.dist-info/entry_points.txt
mkdocs_ko_fi_button_plugin-0.0.3.dist-info/top_level.txt
mkdocs_ko_fi_button_plugin-0.0.3.dist-info/RECORD
