Metadata-Version: 2.1
Name: mkdocs-ko-fi-button-plugin
Version: 0.0.3
Summary: Ko-fi button is a simple plugin that let's you add a Ko-fi button with markdown.
Home-page: https://gitlab.com/berghton/mkdocs-ko-fi-button-plugin
Author: Tony Bergh
Author-email: tony.bergh@gmail.com
License: MIT
Platform: UNKNOWN
Classifier: Programming Language :: Python :: 3
Classifier: License :: OSI Approved :: MIT License
Classifier: Operating System :: OS Independent
Classifier: Development Status :: 3 - Alpha
Requires-Python: >=3.7
Requires-Dist: mkdocs (>=1.0.4)
